{
  "package": {
    "dependencies": {
      "@ag-grid-community/core": "^22.1.1",
      "@ag-grid-community/react": "^22.1.2",
      "@ag-grid-enterprise/all-modules": "^22.1.2",
      "@date-io/core": "^1.3.13",
      "@material-ui/core": "^4.7.2",
      "@material-ui/icons": "^4.5.1",
      "@material-ui/lab": "^4.0.0-alpha.37",
      "@material-ui/pickers": "^3.2.8",
      "@robotlegsjs/signals": "^1.1.0",
      "@testing-library/jest-dom": "^5.11.3",
      "@testing-library/react": "^10.4.8",
      "@testing-library/user-event": "^10.4.1",
      "@testing-library/dom": "^6.16.0",
      "@types/node": "^12.0.0",
      "@types/react": "^16.9.0",
      "@types/react-dom": "^16.9.0",
      "@types/jest": "^25.0.0",
      "@types/react-material-ui-form-validator": "^2.0.5",
      "@types/material-ui": "^0.21.7",
      "@typescript-eslint/eslint-plugin": "^3.9.0",
      "@typescript-eslint/parser": "^3.9.0",
      "clsx": "^1.1.1",
      "codemirror": "^5.56.0",
      "eslint": "^6.8.0",
      "eslint-config-airbnb-typescript": "^8.0.2",
      "eslint-config-prettier": "^6.11.0",
      "eslint-loader": "^4.0.2",
      "eslint-plugin-import": "^2.22.0",
      "eslint-plugin-jsx-a11y": "^6.3.1",
      "eslint-plugin-react": "^7.20.5",
      "eslint-plugin-react-hooks": "^2.5.1",
      "fuse.js": "^3.4.6",
      "history": "^4.10.1",
      "gojs": "^2.1.3",
      "gojs-react": "^1.0.4",
      "jest-bamboo-reporter": "^1.2.1",
      "moment": "^2.24.0",
      "node-sass": "^4.13.1",
      "numeral": "^2.0.6",
      "prettier": "^2.0.5",
      "prop-types": "^15.7.2",
      "ramda": "^0.26.1",
      "react-codemirror2": "^6.0.0",
      "react-dev-utils": "^10.0.0",
      "react-material-ui-form-validator": "^2.0.10",
      "react-router-dom": "^5.1.2",
      "redux": "^4.0.5",
      "redux-logger": "^3.0.6",
      "redux-thunk": "^2.3.0",
      "typeface-roboto": "0.0.75",
      "typescript": "^3.9.7"
    },
    "scripts": {
      "format": "npx prettier --write src/**/*.{js,jsx,ts,tsx} && npx prettier --write *.{js,jsx,ts,tsx,json}",
      "lint": "eslint --fix **/*.{js,jsx,ts,tsx}",
      "lint-list": "eslint **/*.{js,jsx,ts,tsx}"
    }
  }
}
